{"boards": [{"turn": "black", "old_boards": [{"turn": "white", "heuristic": 1000, "pieces": [{"x": 4, "y": 4, "color": "white", "kind": "king"}, {"x": 2, "y": 2, "color": "white", "kind": "queen"}, {"x": 3, "y": 3, "color": "black", "kind": "queen"}, {"x": 1, "y": 1, "color": "black", "kind": "king"}]}, {"turn": "black", "heuristic": -1000, "pieces": [{"x": 4, "y": 4, "color": "white", "kind": "king"}, {"x": 2, "y": 2, "color": "white", "kind": "queen"}, {"x": 3, "y": 3, "color": "black", "kind": "queen"}, {"x": 0, "y": 0, "color": "black", "kind": "king"}]}], "heuristic": 0, "pieces": [{"x": 5, "y": 5, "color": "white", "kind": "king"}, {"x": 2, "y": 2, "color": "white", "kind": "queen"}, {"x": 3, "y": 3, "color": "black", "kind": "queen"}, {"x": 1, "y": 1, "color": "black", "kind": "king"}]}, {"turn": "black", "old_boards": [{"turn": "white", "heuristic": 0, "pieces": [{"x": 4, "y": 4, "color": "white", "kind": "king"}, {"x": 2, "y": 2, "color": "white", "kind": "queen"}, {"x": 3, "y": 3, "color": "black", "kind": "queen"}, {"x": 1, "y": 1, "color": "black", "kind": "king"}]}, {"turn": "black", "heuristic": -1000, "pieces": [{"x": 4, "y": 4, "color": "white", "kind": "king"}, {"x": 2, "y": 2, "color": "white", "kind": "queen"}, {"x": 3, "y": 3, "color": "black", "kind": "queen"}, {"x": 0, "y": 0, "color": "black", "kind": "king"}]}], "heuristic": 0, "pieces": [{"x": 5, "y": 5, "color": "white", "kind": "king"}, {"x": 2, "y": 2, "color": "white", "kind": "queen"}, {"x": 3, "y": 3, "color": "black", "kind": "queen"}, {"x": 1, "y": 1, "color": "black", "kind": "king"}]}, {"turn": "black", "old_boards": [{"turn": "white", "heuristic": 0, "pieces": [{"x": 4, "y": 4, "color": "white", "kind": "king"}, {"x": 2, "y": 2, "color": "white", "kind": "queen"}, {"x": 3, "y": 3, "color": "black", "kind": "queen"}, {"x": 1, "y": 1, "color": "black", "kind": "king"}]}, {"turn": "black", "heuristic": -1000, "pieces": [{"x": 4, "y": 4, "color": "white", "kind": "king"}, {"x": 2, "y": 2, "color": "white", "kind": "queen"}, {"x": 3, "y": 3, "color": "black", "kind": "queen"}, {"x": 0, "y": 0, "color": "black", "kind": "king"}]}], "heuristic": 0, "pieces": [{"x": 4, "y": 4, "color": "white", "kind": "king"}, {"x": 2, "y": 2, "color": "white", "kind": "queen"}, {"x": 3, "y": 3, "color": "black", "kind": "queen"}, {"x": 1, "y": 1, "color": "black", "kind": "king"}]}, {"turn": "black", "old_boards": [{"turn": "white", "heuristic": 0, "pieces": [{"x": 4, "y": 4, "color": "white", "kind": "king"}, {"x": 2, "y": 2, "color": "white", "kind": "queen"}, {"x": 3, "y": 3, "color": "black", "kind": "queen"}, {"x": 1, "y": 1, "color": "black", "kind": "king"}]}, {"turn": "black", "heuristic": -1000, "pieces": [{"x": 4, "y": 4, "color": "white", "kind": "king"}, {"x": 2, "y": 2, "color": "white", "kind": "queen"}, {"x": 3, "y": 3, "color": "black", "kind": "queen"}, {"x": 0, "y": 0, "color": "black", "kind": "king"}]}], "heuristic": -9, "pieces": [{"x": 4, "y": 4, "color": "white", "kind": "king"}, {"x": 3, "y": 3, "color": "white", "kind": "queen"}, {"x": 1, "y": 1, "color": "black", "kind": "king"}]}, {"turn": "black", "old_boards": [{"turn": "white", "heuristic": -9, "pieces": [{"x": 4, "y": 4, "color": "white", "kind": "king"}, {"x": 2, "y": 2, "color": "white", "kind": "queen"}, {"x": 3, "y": 3, "color": "black", "kind": "queen"}, {"x": 1, "y": 1, "color": "black", "kind": "king"}]}, {"turn": "black", "heuristic": -1000, "pieces": [{"x": 4, "y": 4, "color": "white", "kind": "king"}, {"x": 2, "y": 2, "color": "white", "kind": "queen"}, {"x": 3, "y": 3, "color": "black", "kind": "queen"}, {"x": 0, "y": 0, "color": "black", "kind": "king"}]}], "heuristic": 0, "pieces": [{"x": 4, "y": 4, "color": "white", "kind": "king"}, {"x": 1, "y": 1, "color": "white", "kind": "queen"}, {"x": 3, "y": 3, "color": "black", "kind": "queen"}, {"x": 1, "y": 1, "color": "black", "kind": "king"}]}, {"turn": "black", "old_boards": [{"turn": "white", "heuristic": -9, "pieces": [{"x": 4, "y": 4, "color": "white", "kind": "king"}, {"x": 2, "y": 2, "color": "white", "kind": "queen"}, {"x": 3, "y": 3, "color": "black", "kind": "queen"}, {"x": 1, "y": 1, "color": "black", "kind": "king"}]}, {"turn": "black", "heuristic": -1000, "pieces": [{"x": 4, "y": 4, "color": "white", "kind": "king"}, {"x": 2, "y": 2, "color": "white", "kind": "queen"}, {"x": 3, "y": 3, "color": "black", "kind": "queen"}, {"x": 0, "y": 0, "color": "black", "kind": "king"}]}], "heuristic": 0, "pieces": [{"x": 4, "y": 4, "color": "white", "kind": "king"}, {"x": 0, "y": 0, "color": "white", "kind": "queen"}, {"x": 3, "y": 3, "color": "black", "kind": "queen"}, {"x": 1, "y": 1, "color": "black", "kind": "king"}]}, {"turn": "black", "old_boards": [{"turn": "white", "heuristic": -9, "pieces": [{"x": 4, "y": 4, "color": "white", "kind": "king"}, {"x": 2, "y": 2, "color": "white", "kind": "queen"}, {"x": 3, "y": 3, "color": "black", "kind": "queen"}, {"x": 1, "y": 1, "color": "black", "kind": "king"}]}, {"turn": "black", "heuristic": -1000, "pieces": [{"x": 4, "y": 4, "color": "white", "kind": "king"}, {"x": 2, "y": 2, "color": "white", "kind": "queen"}, {"x": 3, "y": 3, "color": "black", "kind": "queen"}, {"x": 0, "y": 0, "color": "black", "kind": "king"}]}], "heuristic": 0, "pieces": [{"x": 4, "y": 4, "color": "white", "kind": "king"}, {"x": 2, "y": 2, "color": "white", "kind": "queen"}, {"x": 3, "y": 3, "color": "black", "kind": "queen"}, {"x": 1, "y": 1, "color": "black", "kind": "king"}]}, {"turn": "black", "old_boards": [{"turn": "white", "heuristic": -9, "pieces": [{"x": 4, "y": 4, "color": "white", "kind": "king"}, {"x": 2, "y": 2, "color": "white", "kind": "queen"}, {"x": 3, "y": 3, "color": "black", "kind": "queen"}, {"x": 1, "y": 1, "color": "black", "kind": "king"}]}, {"turn": "black", "heuristic": -1000, "pieces": [{"x": 4, "y": 4, "color": "white", "kind": "king"}, {"x": 2, "y": 2, "color": "white", "kind": "queen"}, {"x": 3, "y": 3, "color": "black", "kind": "queen"}, {"x": 0, "y": 0, "color": "black", "kind": "king"}]}], "heuristic": 0, "pieces": [{"x": 4, "y": 4, "color": "white", "kind": "king"}, {"x": 2, "y": 2, "color": "white", "kind": "queen"}, {"x": 3, "y": 3, "color": "black", "kind": "queen"}, {"x": 1, "y": 1, "color": "black", "kind": "king"}]}, {"turn": "black", "old_boards": [{"turn": "white", "heuristic": -9, "pieces": [{"x": 4, "y": 4, "color": "white", "kind": "king"}, {"x": 2, "y": 2, "color": "white", "kind": "queen"}, {"x": 3, "y": 3, "color": "black", "kind": "queen"}, {"x": 1, "y": 1, "color": "black", "kind": "king"}]}, {"turn": "black", "heuristic": -1000, "pieces": [{"x": 4, "y": 4, "color": "white", "kind": "king"}, {"x": 2, "y": 2, "color": "white", "kind": "queen"}, {"x": 3, "y": 3, "color": "black", "kind": "queen"}, {"x": 0, "y": 0, "color": "black", "kind": "king"}]}], "heuristic": 0, "pieces": [{"x": 4, "y": 4, "color": "white", "kind": "king"}, {"x": 2, "y": 2, "color": "white", "kind": "queen"}, {"x": 3, "y": 3, "color": "black", "kind": "queen"}, {"x": 1, "y": 1, "color": "black", "kind": "king"}]}, {"turn": "black", "old_boards": [{"turn": "white", "heuristic": -9, "pieces": [{"x": 4, "y": 4, "color": "white", "kind": "king"}, {"x": 2, "y": 2, "color": "white", "kind": "queen"}, {"x": 3, "y": 3, "color": "black", "kind": "queen"}, {"x": 1, "y": 1, "color": "black", "kind": "king"}]}, {"turn": "black", "heuristic": -1000, "pieces": [{"x": 4, "y": 4, "color": "white", "kind": "king"}, {"x": 2, "y": 2, "color": "white", "kind": "queen"}, {"x": 3, "y": 3, "color": "black", "kind": "queen"}, {"x": 0, "y": 0, "color": "black", "kind": "king"}]}], "heuristic": 0, "pieces": [{"x": 4, "y": 4, "color": "white", "kind": "king"}, {"x": 2, "y": 2, "color": "white", "kind": "queen"}, {"x": 3, "y": 3, "color": "black", "kind": "queen"}, {"x": 1, "y": 1, "color": "black", "kind": "king"}]}, {"turn": "black", "old_boards": [{"turn": "white", "heuristic": -9, "pieces": [{"x": 4, "y": 4, "color": "white", "kind": "king"}, {"x": 2, "y": 2, "color": "white", "kind": "queen"}, {"x": 3, "y": 3, "color": "black", "kind": "queen"}, {"x": 1, "y": 1, "color": "black", "kind": "king"}]}, {"turn": "black", "heuristic": -1000, "pieces": [{"x": 4, "y": 4, "color": "white", "kind": "king"}, {"x": 2, "y": 2, "color": "white", "kind": "queen"}, {"x": 3, "y": 3, "color": "black", "kind": "queen"}, {"x": 0, "y": 0, "color": "black", "kind": "king"}]}], "heuristic": 0, "pieces": [{"x": 4, "y": 4, "color": "white", "kind": "king"}, {"x": 2, "y": 2, "color": "white", "kind": "queen"}, {"x": 3, "y": 3, "color": "black", "kind": "queen"}, {"x": 1, "y": 1, "color": "black", "kind": "king"}]}, {"turn": "black", "old_boards": [{"turn": "white", "heuristic": -9, "pieces": [{"x": 4, "y": 4, "color": "white", "kind": "king"}, {"x": 2, "y": 2, "color": "white", "kind": "queen"}, {"x": 3, "y": 3, "color": "black", "kind": "queen"}, {"x": 1, "y": 1, "color": "black", "kind": "king"}]}, {"turn": "black", "heuristic": -1000, "pieces": [{"x": 4, "y": 4, "color": "white", "kind": "king"}, {"x": 2, "y": 2, "color": "white", "kind": "queen"}, {"x": 3, "y": 3, "color": "black", "kind": "queen"}, {"x": 0, "y": 0, "color": "black", "kind": "king"}]}], "heuristic": 0, "pieces": [{"x": 4, "y": 4, "color": "white", "kind": "king"}, {"x": 2, "y": 2, "color": "white", "kind": "queen"}, {"x": 3, "y": 3, "color": "black", "kind": "queen"}, {"x": 1, "y": 1, "color": "black", "kind": "king"}]}, {"turn": "black", "old_boards": [{"turn": "white", "heuristic": -9, "pieces": [{"x": 4, "y": 4, "color": "white", "kind": "king"}, {"x": 2, "y": 2, "color": "white", "kind": "queen"}, {"x": 3, "y": 3, "color": "black", "kind": "queen"}, {"x": 1, "y": 1, "color": "black", "kind": "king"}]}, {"turn": "black", "heuristic": -1000, "pieces": [{"x": 4, "y": 4, "color": "white", "kind": "king"}, {"x": 2, "y": 2, "color": "white", "kind": "queen"}, {"x": 3, "y": 3, "color": "black", "kind": "queen"}, {"x": 0, "y": 0, "color": "black", "kind": "king"}]}], "heuristic": 0, "pieces": [{"x": 4, "y": 4, "color": "white", "kind": "king"}, {"x": 2, "y": 2, "color": "white", "kind": "queen"}, {"x": 3, "y": 3, "color": "black", "kind": "queen"}, {"x": 1, "y": 1, "color": "black", "kind": "king"}]}, {"turn": "black", "old_boards": [{"turn": "white", "heuristic": -9, "pieces": [{"x": 4, "y": 4, "color": "white", "kind": "king"}, {"x": 2, "y": 2, "color": "white", "kind": "queen"}, {"x": 3, "y": 3, "color": "black", "kind": "queen"}, {"x": 1, "y": 1, "color": "black", "kind": "king"}]}, {"turn": "black", "heuristic": -1000, "pieces": [{"x": 4, "y": 4, "color": "white", "kind": "king"}, {"x": 2, "y": 2, "color": "white", "kind": "queen"}, {"x": 3, "y": 3, "color": "black", "kind": "queen"}, {"x": 0, "y": 0, "color": "black", "kind": "king"}]}], "heuristic": 0, "pieces": [{"x": 4, "y": 4, "color": "white", "kind": "king"}, {"x": 1, "y": 1, "color": "white", "kind": "queen"}, {"x": 3, "y": 3, "color": "black", "kind": "queen"}, {"x": 1, "y": 1, "color": "black", "kind": "king"}]}, {"turn": "black", "old_boards": [{"turn": "white", "heuristic": -9, "pieces": [{"x": 4, "y": 4, "color": "white", "kind": "king"}, {"x": 2, "y": 2, "color": "white", "kind": "queen"}, {"x": 3, "y": 3, "color": "black", "kind": "queen"}, {"x": 1, "y": 1, "color": "black", "kind": "king"}]}, {"turn": "black", "heuristic": -1000, "pieces": [{"x": 4, "y": 4, "color": "white", "kind": "king"}, {"x": 2, "y": 2, "color": "white", "kind": "queen"}, {"x": 3, "y": 3, "color": "black", "kind": "queen"}, {"x": 0, "y": 0, "color": "black", "kind": "king"}]}], "heuristic": 0, "pieces": [{"x": 4, "y": 4, "color": "white", "kind": "king"}, {"x": 0, "y": 0, "color": "white", "kind": "queen"}, {"x": 3, "y": 3, "color": "black", "kind": "queen"}, {"x": 1, "y": 1, "color": "black", "kind": "king"}]}, {"turn": "black", "old_boards": [{"turn": "white", "heuristic": -9, "pieces": [{"x": 4, "y": 4, "color": "white", "kind": "king"}, {"x": 2, "y": 2, "color": "white", "kind": "queen"}, {"x": 3, "y": 3, "color": "black", "kind": "queen"}, {"x": 1, "y": 1, "color": "black", "kind": "king"}]}, {"turn": "black", "heuristic": -1000, "pieces": [{"x": 4, "y": 4, "color": "white", "kind": "king"}, {"x": 2, "y": 2, "color": "white", "kind": "queen"}, {"x": 3, "y": 3, "color": "black", "kind": "queen"}, {"x": 0, "y": 0, "color": "black", "kind": "king"}]}], "heuristic": 0, "pieces": [{"x": 4, "y": 4, "color": "white", "kind": "king"}, {"x": 3, "y": 3, "color": "white", "kind": "queen"}, {"x": 3, "y": 3, "color": "black", "kind": "queen"}, {"x": 1, "y": 1, "color": "black", "kind": "king"}]}, {"turn": "black", "old_boards": [{"turn": "white", "heuristic": 1000, "pieces": [{"x": 4, "y": 4, "color": "white", "kind": "king"}, {"x": 2, "y": 2, "color": "white", "kind": "queen"}, {"x": 3, "y": 3, "color": "black", "kind": "queen"}, {"x": 1, "y": 1, "color": "black", "kind": "king"}]}, {"turn": "black", "heuristic": -9, "pieces": [{"x": 4, "y": 4, "color": "white", "kind": "king"}, {"x": 2, "y": 2, "color": "white", "kind": "queen"}, {"x": 3, "y": 3, "color": "black", "kind": "queen"}, {"x": 0, "y": 0, "color": "black", "kind": "king"}]}], "heuristic": 0, "pieces": [{"x": 5, "y": 5, "color": "white", "kind": "king"}, {"x": 2, "y": 2, "color": "white", "kind": "queen"}, {"x": 3, "y": 3, "color": "black", "kind": "queen"}, {"x": 1, "y": 1, "color": "black", "kind": "king"}]}, {"turn": "black", "old_boards": [{"turn": "white", "heuristic": 0, "pieces": [{"x": 4, "y": 4, "color": "white", "kind": "king"}, {"x": 2, "y": 2, "color": "white", "kind": "queen"}, {"x": 3, "y": 3, "color": "black", "kind": "queen"}, {"x": 1, "y": 1, "color": "black", "kind": "king"}]}, {"turn": "black", "heuristic": -9, "pieces": [{"x": 4, "y": 4, "color": "white", "kind": "king"}, {"x": 2, "y": 2, "color": "white", "kind": "queen"}, {"x": 3, "y": 3, "color": "black", "kind": "queen"}, {"x": 0, "y": 0, "color": "black", "kind": "king"}]}], "heuristic": 0, "pieces": [{"x": 5, "y": 5, "color": "white", "kind": "king"}, {"x": 2, "y": 2, "color": "white", "kind": "queen"}, {"x": 3, "y": 3, "color": "black", "kind": "queen"}, {"x": 1, "y": 1, "color": "black", "kind": "king"}]}, {"turn": "black", "old_boards": [{"turn": "white", "heuristic": 0, "pieces": [{"x": 4, "y": 4, "color": "white", "kind": "king"}, {"x": 2, "y": 2, "color": "white", "kind": "queen"}, {"x": 3, "y": 3, "color": "black", "kind": "queen"}, {"x": 1, "y": 1, "color": "black", "kind": "king"}]}, {"turn": "black", "heuristic": -9, "pieces": [{"x": 4, "y": 4, "color": "white", "kind": "king"}, {"x": 2, "y": 2, "color": "white", "kind": "queen"}, {"x": 3, "y": 3, "color": "black", "kind": "queen"}, {"x": 0, "y": 0, "color": "black", "kind": "king"}]}], "heuristic": 0, "pieces": [{"x": 4, "y": 4, "color": "white", "kind": "king"}, {"x": 2, "y": 2, "color": "white", "kind": "queen"}, {"x": 3, "y": 3, "color": "black", "kind": "queen"}, {"x": 1, "y": 1, "color": "black", "kind": "king"}]}, {"turn": "black", "old_boards": [{"turn": "white", "heuristic": 0, "pieces": [{"x": 4, "y": 4, "color": "white", "kind": "king"}, {"x": 2, "y": 2, "color": "white", "kind": "queen"}, {"x": 3, "y": 3, "color": "black", "kind": "queen"}, {"x": 1, "y": 1, "color": "black", "kind": "king"}]}, {"turn": "black", "heuristic": -9, "pieces": [{"x": 4, "y": 4, "color": "white", "kind": "king"}, {"x": 2, "y": 2, "color": "white", "kind": "queen"}, {"x": 3, "y": 3, "color": "black", "kind": "queen"}, {"x": 0, "y": 0, "color": "black", "kind": "king"}]}], "heuristic": -9, "pieces": [{"x": 4, "y": 4, "color": "white", "kind": "king"}, {"x": 3, "y": 3, "color": "white", "kind": "queen"}, {"x": 1, "y": 1, "color": "black", "kind": "king"}]}, {"turn": "black", "old_boards": [{"turn": "white", "heuristic": -9, "pieces": [{"x": 4, "y": 4, "color": "white", "kind": "king"}, {"x": 2, "y": 2, "color": "white", "kind": "queen"}, {"x": 3, "y": 3, "color": "black", "kind": "queen"}, {"x": 1, "y": 1, "color": "black", "kind": "king"}]}, {"turn": "black", "heuristic": -9, "pieces": [{"x": 4, "y": 4, "color": "white", "kind": "king"}, {"x": 2, "y": 2, "color": "white", "kind": "queen"}, {"x": 3, "y": 3, "color": "black", "kind": "queen"}, {"x": 0, "y": 0, "color": "black", "kind": "king"}]}], "heuristic": 0, "pieces": [{"x": 4, "y": 4, "color": "white", "kind": "king"}, {"x": 1, "y": 1, "color": "white", "kind": "queen"}, {"x": 3, "y": 3, "color": "black", "kind": "queen"}, {"x": 1, "y": 1, "color": "black", "kind": "king"}]}, {"turn": "black", "old_boards": [{"turn": "white", "heuristic": -9, "pieces": [{"x": 4, "y": 4, "color": "white", "kind": "king"}, {"x": 2, "y": 2, "color": "white", "kind": "queen"}, {"x": 3, "y": 3, "color": "black", "kind": "queen"}, {"x": 1, "y": 1, "color": "black", "kind": "king"}]}, {"turn": "black", "heuristic": -9, "pieces": [{"x": 4, "y": 4, "color": "white", "kind": "king"}, {"x": 2, "y": 2, "color": "white", "kind": "queen"}, {"x": 3, "y": 3, "color": "black", "kind": "queen"}, {"x": 0, "y": 0, "color": "black", "kind": "king"}]}], "heuristic": 0, "pieces": [{"x": 4, "y": 4, "color": "white", "kind": "king"}, {"x": 0, "y": 0, "color": "white", "kind": "queen"}, {"x": 3, "y": 3, "color": "black", "kind": "queen"}, {"x": 1, "y": 1, "color": "black", "kind": "king"}]}, {"turn": "black", "old_boards": [{"turn": "white", "heuristic": -9, "pieces": [{"x": 4, "y": 4, "color": "white", "kind": "king"}, {"x": 2, "y": 2, "color": "white", "kind": "queen"}, {"x": 3, "y": 3, "color": "black", "kind": "queen"}, {"x": 1, "y": 1, "color": "black", "kind": "king"}]}, {"turn": "black", "heuristic": -9, "pieces": [{"x": 4, "y": 4, "color": "white", "kind": "king"}, {"x": 2, "y": 2, "color": "white", "kind": "queen"}, {"x": 3, "y": 3, "color": "black", "kind": "queen"}, {"x": 0, "y": 0, "color": "black", "kind": "king"}]}], "heuristic": 0, "pieces": [{"x": 4, "y": 4, "color": "white", "kind": "king"}, {"x": 2, "y": 2, "color": "white", "kind": "queen"}, {"x": 3, "y": 3, "color": "black", "kind": "queen"}, {"x": 1, "y": 1, "color": "black", "kind": "king"}]}, {"turn": "black", "old_boards": [{"turn": "white", "heuristic": -9, "pieces": [{"x": 4, "y": 4, "color": "white", "kind": "king"}, {"x": 2, "y": 2, "color": "white", "kind": "queen"}, {"x": 3, "y": 3, "color": "black", "kind": "queen"}, {"x": 1, "y": 1, "color": "black", "kind": "king"}]}, {"turn": "black", "heuristic": -9, "pieces": [{"x": 4, "y": 4, "color": "white", "kind": "king"}, {"x": 2, "y": 2, "color": "white", "kind": "queen"}, {"x": 3, "y": 3, "color": "black", "kind": "queen"}, {"x": 0, "y": 0, "color": "black", "kind": "king"}]}], "heuristic": 0, "pieces": [{"x": 4, "y": 4, "color": "white", "kind": "king"}, {"x": 2, "y": 2, "color": "white", "kind": "queen"}, {"x": 3, "y": 3, "color": "black", "kind": "queen"}, {"x": 1, "y": 1, "color": "black", "kind": "king"}]}, {"turn": "black", "old_boards": [{"turn": "white", "heuristic": -9, "pieces": [{"x": 4, "y": 4, "color": "white", "kind": "king"}, {"x": 2, "y": 2, "color": "white", "kind": "queen"}, {"x": 3, "y": 3, "color": "black", "kind": "queen"}, {"x": 1, "y": 1, "color": "black", "kind": "king"}]}, {"turn": "black", "heuristic": -9, "pieces": [{"x": 4, "y": 4, "color": "white", "kind": "king"}, {"x": 2, "y": 2, "color": "white", "kind": "queen"}, {"x": 3, "y": 3, "color": "black", "kind": "queen"}, {"x": 0, "y": 0, "color": "black", "kind": "king"}]}], "heuristic": 0, "pieces": [{"x": 4, "y": 4, "color": "white", "kind": "king"}, {"x": 2, "y": 2, "color": "white", "kind": "queen"}, {"x": 3, "y": 3, "color": "black", "kind": "queen"}, {"x": 1, "y": 1, "color": "black", "kind": "king"}]}, {"turn": "black", "old_boards": [{"turn": "white", "heuristic": -9, "pieces": [{"x": 4, "y": 4, "color": "white", "kind": "king"}, {"x": 2, "y": 2, "color": "white", "kind": "queen"}, {"x": 3, "y": 3, "color": "black", "kind": "queen"}, {"x": 1, "y": 1, "color": "black", "kind": "king"}]}, {"turn": "black", "heuristic": -9, "pieces": [{"x": 4, "y": 4, "color": "white", "kind": "king"}, {"x": 2, "y": 2, "color": "white", "kind": "queen"}, {"x": 3, "y": 3, "color": "black", "kind": "queen"}, {"x": 0, "y": 0, "color": "black", "kind": "king"}]}], "heuristic": 0, "pieces": [{"x": 4, "y": 4, "color": "white", "kind": "king"}, {"x": 2, "y": 2, "color": "white", "kind": "queen"}, {"x": 3, "y": 3, "color": "black", "kind": "queen"}, {"x": 1, "y": 1, "color": "black", "kind": "king"}]}, {"turn": "black", "old_boards": [{"turn": "white", "heuristic": -9, "pieces": [{"x": 4, "y": 4, "color": "white", "kind": "king"}, {"x": 2, "y": 2, "color": "white", "kind": "queen"}, {"x": 3, "y": 3, "color": "black", "kind": "queen"}, {"x": 1, "y": 1, "color": "black", "kind": "king"}]}, {"turn": "black", "heuristic": -9, "pieces": [{"x": 4, "y": 4, "color": "white", "kind": "king"}, {"x": 2, "y": 2, "color": "white", "kind": "queen"}, {"x": 3, "y": 3, "color": "black", "kind": "queen"}, {"x": 0, "y": 0, "color": "black", "kind": "king"}]}], "heuristic": 0, "pieces": [{"x": 4, "y": 4, "color": "white", "kind": "king"}, {"x": 2, "y": 2, "color": "white", "kind": "queen"}, {"x": 3, "y": 3, "color": "black", "kind": "queen"}, {"x": 1, "y": 1, "color": "black", "kind": "king"}]}, {"turn": "black", "old_boards": [{"turn": "white", "heuristic": -9, "pieces": [{"x": 4, "y": 4, "color": "white", "kind": "king"}, {"x": 2, "y": 2, "color": "white", "kind": "queen"}, {"x": 3, "y": 3, "color": "black", "kind": "queen"}, {"x": 1, "y": 1, "color": "black", "kind": "king"}]}, {"turn": "black", "heuristic": -9, "pieces": [{"x": 4, "y": 4, "color": "white", "kind": "king"}, {"x": 2, "y": 2, "color": "white", "kind": "queen"}, {"x": 3, "y": 3, "color": "black", "kind": "queen"}, {"x": 0, "y": 0, "color": "black", "kind": "king"}]}], "heuristic": 0, "pieces": [{"x": 4, "y": 4, "color": "white", "kind": "king"}, {"x": 2, "y": 2, "color": "white", "kind": "queen"}, {"x": 3, "y": 3, "color": "black", "kind": "queen"}, {"x": 1, "y": 1, "color": "black", "kind": "king"}]}, {"turn": "black", "old_boards": [{"turn": "white", "heuristic": -9, "pieces": [{"x": 4, "y": 4, "color": "white", "kind": "king"}, {"x": 2, "y": 2, "color": "white", "kind": "queen"}, {"x": 3, "y": 3, "color": "black", "kind": "queen"}, {"x": 1, "y": 1, "color": "black", "kind": "king"}]}, {"turn": "black", "heuristic": -9, "pieces": [{"x": 4, "y": 4, "color": "white", "kind": "king"}, {"x": 2, "y": 2, "color": "white", "kind": "queen"}, {"x": 3, "y": 3, "color": "black", "kind": "queen"}, {"x": 0, "y": 0, "color": "black", "kind": "king"}]}], "heuristic": 0, "pieces": [{"x": 4, "y": 4, "color": "white", "kind": "king"}, {"x": 2, "y": 2, "color": "white", "kind": "queen"}, {"x": 3, "y": 3, "color": "black", "kind": "queen"}, {"x": 1, "y": 1, "color": "black", "kind": "king"}]}, {"turn": "black", "old_boards": [{"turn": "white", "heuristic": -9, "pieces": [{"x": 4, "y": 4, "color": "white", "kind": "king"}, {"x": 2, "y": 2, "color": "white", "kind": "queen"}, {"x": 3, "y": 3, "color": "black", "kind": "queen"}, {"x": 1, "y": 1, "color": "black", "kind": "king"}]}, {"turn": "black", "heuristic": -9, "pieces": [{"x": 4, "y": 4, "color": "white", "kind": "king"}, {"x": 2, "y": 2, "color": "white", "kind": "queen"}, {"x": 3, "y": 3, "color": "black", "kind": "queen"}, {"x": 0, "y": 0, "color": "black", "kind": "king"}]}], "heuristic": 0, "pieces": [{"x": 4, "y": 4, "color": "white", "kind": "king"}, {"x": 1, "y": 1, "color": "white", "kind": "queen"}, {"x": 3, "y": 3, "color": "black", "kind": "queen"}, {"x": 1, "y": 1, "color": "black", "kind": "king"}]}, {"turn": "black", "old_boards": [{"turn": "white", "heuristic": -9, "pieces": [{"x": 4, "y": 4, "color": "white", "kind": "king"}, {"x": 2, "y": 2, "color": "white", "kind": "queen"}, {"x": 3, "y": 3, "color": "black", "kind": "queen"}, {"x": 1, "y": 1, "color": "black", "kind": "king"}]}, {"turn": "black", "heuristic": -9, "pieces": [{"x": 4, "y": 4, "color": "white", "kind": "king"}, {"x": 2, "y": 2, "color": "white", "kind": "queen"}, {"x": 3, "y": 3, "color": "black", "kind": "queen"}, {"x": 0, "y": 0, "color": "black", "kind": "king"}]}], "heuristic": 0, "pieces": [{"x": 4, "y": 4, "color": "white", "kind": "king"}, {"x": 0, "y": 0, "color": "white", "kind": "queen"}, {"x": 3, "y": 3, "color": "black", "kind": "queen"}, {"x": 1, "y": 1, "color": "black", "kind": "king"}]}, {"turn": "black", "old_boards": [{"turn": "white", "heuristic": -9, "pieces": [{"x": 4, "y": 4, "color": "white", "kind": "king"}, {"x": 2, "y": 2, "color": "white", "kind": "queen"}, {"x": 3, "y": 3, "color": "black", "kind": "queen"}, {"x": 1, "y": 1, "color": "black", "kind": "king"}]}, {"turn": "black", "heuristic": -9, "pieces": [{"x": 4, "y": 4, "color": "white", "kind": "king"}, {"x": 2, "y": 2, "color": "white", "kind": "queen"}, {"x": 3, "y": 3, "color": "black", "kind": "queen"}, {"x": 0, "y": 0, "color": "black", "kind": "king"}]}], "heuristic": 0, "pieces": [{"x": 4, "y": 4, "color": "white", "kind": "king"}, {"x": 3, "y": 3, "color": "white", "kind": "queen"}, {"x": 3, "y": 3, "color": "black", "kind": "queen"}, {"x": 1, "y": 1, "color": "black", "kind": "king"}]}, {"turn": "black", "old_boards": [{"turn": "white", "heuristic": 1000, "pieces": [{"x": 4, "y": 4, "color": "white", "kind": "king"}, {"x": 2, "y": 2, "color": "white", "kind": "queen"}, {"x": 3, "y": 3, "color": "black", "kind": "queen"}, {"x": 0, "y": 0, "color": "black", "kind": "king"}]}, {"turn": "black", "heuristic": -9, "pieces": [{"x": 4, "y": 4, "color": "white", "kind": "king"}, {"x": 2, "y": 2, "color": "white", "kind": "queen"}, {"x": 3, "y": 3, "color": "black", "kind": "queen"}, {"x": 0, "y": 0, "color": "black", "kind": "king"}]}], "heuristic": 0, "pieces": [{"x": 5, "y": 5, "color": "white", "kind": "king"}, {"x": 2, "y": 2, "color": "white", "kind": "queen"}, {"x": 3, "y": 3, "color": "black", "kind": "queen"}, {"x": 0, "y": 0, "color": "black", "kind": "king"}]}, {"turn": "black", "old_boards": [{"turn": "white", "heuristic": 0, "pieces": [{"x": 4, "y": 4, "color": "white", "kind": "king"}, {"x": 2, "y": 2, "color": "white", "kind": "queen"}, {"x": 3, "y": 3, "color": "black", "kind": "queen"}, {"x": 0, "y": 0, "color": "black", "kind": "king"}]}, {"turn": "black", "heuristic": -9, "pieces": [{"x": 4, "y": 4, "color": "white", "kind": "king"}, {"x": 2, "y": 2, "color": "white", "kind": "queen"}, {"x": 3, "y": 3, "color": "black", "kind": "queen"}, {"x": 0, "y": 0, "color": "black", "kind": "king"}]}], "heuristic": 0, "pieces": [{"x": 5, "y": 5, "color": "white", "kind": "king"}, {"x": 2, "y": 2, "color": "white", "kind": "queen"}, {"x": 3, "y": 3, "color": "black", "kind": "queen"}, {"x": 0, "y": 0, "color": "black", "kind": "king"}]}, {"turn": "black", "old_boards": [{"turn": "white", "heuristic": 0, "pieces": [{"x": 4, "y": 4, "color": "white", "kind": "king"}, {"x": 2, "y": 2, "color": "white", "kind": "queen"}, {"x": 3, "y": 3, "color": "black", "kind": "queen"}, {"x": 0, "y": 0, "color": "black", "kind": "king"}]}, {"turn": "black", "heuristic": -9, "pieces": [{"x": 4, "y": 4, "color": "white", "kind": "king"}, {"x": 2, "y": 2, "color": "white", "kind": "queen"}, {"x": 3, "y": 3, "color": "black", "kind": "queen"}, {"x": 0, "y": 0, "color": "black", "kind": "king"}]}], "heuristic": 0, "pieces": [{"x": 4, "y": 4, "color": "white", "kind": "king"}, {"x": 2, "y": 2, "color": "white", "kind": "queen"}, {"x": 3, "y": 3, "color": "black", "kind": "queen"}, {"x": 0, "y": 0, "color": "black", "kind": "king"}]}, {"turn": "black", "old_boards": [{"turn": "white", "heuristic": 0, "pieces": [{"x": 4, "y": 4, "color": "white", "kind": "king"}, {"x": 2, "y": 2, "color": "white", "kind": "queen"}, {"x": 3, "y": 3, "color": "black", "kind": "queen"}, {"x": 0, "y": 0, "color": "black", "kind": "king"}]}, {"turn": "black", "heuristic": -9, "pieces": [{"x": 4, "y": 4, "color": "white", "kind": "king"}, {"x": 2, "y": 2, "color": "white", "kind": "queen"}, {"x": 3, "y": 3, "color": "black", "kind": "queen"}, {"x": 0, "y": 0, "color": "black", "kind": "king"}]}], "heuristic": -9, "pieces": [{"x": 4, "y": 4, "color": "white", "kind": "king"}, {"x": 3, "y": 3, "color": "white", "kind": "queen"}, {"x": 0, "y": 0, "color": "black", "kind": "king"}]}, {"turn": "black", "old_boards": [{"turn": "white", "heuristic": -9, "pieces": [{"x": 4, "y": 4, "color": "white", "kind": "king"}, {"x": 2, "y": 2, "color": "white", "kind": "queen"}, {"x": 3, "y": 3, "color": "black", "kind": "queen"}, {"x": 0, "y": 0, "color": "black", "kind": "king"}]}, {"turn": "black", "heuristic": -9, "pieces": [{"x": 4, "y": 4, "color": "white", "kind": "king"}, {"x": 2, "y": 2, "color": "white", "kind": "queen"}, {"x": 3, "y": 3, "color": "black", "kind": "queen"}, {"x": 0, "y": 0, "color": "black", "kind": "king"}]}], "heuristic": 0, "pieces": [{"x": 4, "y": 4, "color": "white", "kind": "king"}, {"x": 1, "y": 1, "color": "white", "kind": "queen"}, {"x": 3, "y": 3, "color": "black", "kind": "queen"}, {"x": 0, "y": 0, "color": "black", "kind": "king"}]}, {"turn": "black", "old_boards": [{"turn": "white", "heuristic": -9, "pieces": [{"x": 4, "y": 4, "color": "white", "kind": "king"}, {"x": 2, "y": 2, "color": "white", "kind": "queen"}, {"x": 3, "y": 3, "color": "black", "kind": "queen"}, {"x": 0, "y": 0, "color": "black", "kind": "king"}]}, {"turn": "black", "heuristic": -9, "pieces": [{"x": 4, "y": 4, "color": "white", "kind": "king"}, {"x": 2, "y": 2, "color": "white", "kind": "queen"}, {"x": 3, "y": 3, "color": "black", "kind": "queen"}, {"x": 0, "y": 0, "color": "black", "kind": "king"}]}], "heuristic": 0, "pieces": [{"x": 4, "y": 4, "color": "white", "kind": "king"}, {"x": 0, "y": 0, "color": "white", "kind": "queen"}, {"x": 3, "y": 3, "color": "black", "kind": "queen"}, {"x": 0, "y": 0, "color": "black", "kind": "king"}]}, {"turn": "black", "old_boards": [{"turn": "white", "heuristic": -9, "pieces": [{"x": 4, "y": 4, "color": "white", "kind": "king"}, {"x": 2, "y": 2, "color": "white", "kind": "queen"}, {"x": 3, "y": 3, "color": "black", "kind": "queen"}, {"x": 0, "y": 0, "color": "black", "kind": "king"}]}, {"turn": "black", "heuristic": -9, "pieces": [{"x": 4, "y": 4, "color": "white", "kind": "king"}, {"x": 2, "y": 2, "color": "white", "kind": "queen"}, {"x": 3, "y": 3, "color": "black", "kind": "queen"}, {"x": 0, "y": 0, "color": "black", "kind": "king"}]}], "heuristic": 0, "pieces": [{"x": 4, "y": 4, "color": "white", "kind": "king"}, {"x": 2, "y": 2, "color": "white", "kind": "queen"}, {"x": 3, "y": 3, "color": "black", "kind": "queen"}, {"x": 0, "y": 0, "color": "black", "kind": "king"}]}, {"turn": "black", "old_boards": [{"turn": "white", "heuristic": -9, "pieces": [{"x": 4, "y": 4, "color": "white", "kind": "king"}, {"x": 2, "y": 2, "color": "white", "kind": "queen"}, {"x": 3, "y": 3, "color": "black", "kind": "queen"}, {"x": 0, "y": 0, "color": "black", "kind": "king"}]}, {"turn": "black", "heuristic": -9, "pieces": [{"x": 4, "y": 4, "color": "white", "kind": "king"}, {"x": 2, "y": 2, "color": "white", "kind": "queen"}, {"x": 3, "y": 3, "color": "black", "kind": "queen"}, {"x": 0, "y": 0, "color": "black", "kind": "king"}]}], "heuristic": 0, "pieces": [{"x": 4, "y": 4, "color": "white", "kind": "king"}, {"x": 2, "y": 2, "color": "white", "kind": "queen"}, {"x": 3, "y": 3, "color": "black", "kind": "queen"}, {"x": 0, "y": 0, "color": "black", "kind": "king"}]}, {"turn": "black", "old_boards": [{"turn": "white", "heuristic": -9, "pieces": [{"x": 4, "y": 4, "color": "white", "kind": "king"}, {"x": 2, "y": 2, "color": "white", "kind": "queen"}, {"x": 3, "y": 3, "color": "black", "kind": "queen"}, {"x": 0, "y": 0, "color": "black", "kind": "king"}]}, {"turn": "black", "heuristic": -9, "pieces": [{"x": 4, "y": 4, "color": "white", "kind": "king"}, {"x": 2, "y": 2, "color": "white", "kind": "queen"}, {"x": 3, "y": 3, "color": "black", "kind": "queen"}, {"x": 0, "y": 0, "color": "black", "kind": "king"}]}], "heuristic": 0, "pieces": [{"x": 4, "y": 4, "color": "white", "kind": "king"}, {"x": 2, "y": 2, "color": "white", "kind": "queen"}, {"x": 3, "y": 3, "color": "black", "kind": "queen"}, {"x": 0, "y": 0, "color": "black", "kind": "king"}]}, {"turn": "black", "old_boards": [{"turn": "white", "heuristic": -9, "pieces": [{"x": 4, "y": 4, "color": "white", "kind": "king"}, {"x": 2, "y": 2, "color": "white", "kind": "queen"}, {"x": 3, "y": 3, "color": "black", "kind": "queen"}, {"x": 0, "y": 0, "color": "black", "kind": "king"}]}, {"turn": "black", "heuristic": -9, "pieces": [{"x": 4, "y": 4, "color": "white", "kind": "king"}, {"x": 2, "y": 2, "color": "white", "kind": "queen"}, {"x": 3, "y": 3, "color": "black", "kind": "queen"}, {"x": 0, "y": 0, "color": "black", "kind": "king"}]}], "heuristic": 0, "pieces": [{"x": 4, "y": 4, "color": "white", "kind": "king"}, {"x": 2, "y": 2, "color": "white", "kind": "queen"}, {"x": 3, "y": 3, "color": "black", "kind": "queen"}, {"x": 0, "y": 0, "color": "black", "kind": "king"}]}, {"turn": "black", "old_boards": [{"turn": "white", "heuristic": -9, "pieces": [{"x": 4, "y": 4, "color": "white", "kind": "king"}, {"x": 2, "y": 2, "color": "white", "kind": "queen"}, {"x": 3, "y": 3, "color": "black", "kind": "queen"}, {"x": 0, "y": 0, "color": "black", "kind": "king"}]}, {"turn": "black", "heuristic": -9, "pieces": [{"x": 4, "y": 4, "color": "white", "kind": "king"}, {"x": 2, "y": 2, "color": "white", "kind": "queen"}, {"x": 3, "y": 3, "color": "black", "kind": "queen"}, {"x": 0, "y": 0, "color": "black", "kind": "king"}]}], "heuristic": 0, "pieces": [{"x": 4, "y": 4, "color": "white", "kind": "king"}, {"x": 2, "y": 2, "color": "white", "kind": "queen"}, {"x": 3, "y": 3, "color": "black", "kind": "queen"}, {"x": 0, "y": 0, "color": "black", "kind": "king"}]}, {"turn": "black", "old_boards": [{"turn": "white", "heuristic": -9, "pieces": [{"x": 4, "y": 4, "color": "white", "kind": "king"}, {"x": 2, "y": 2, "color": "white", "kind": "queen"}, {"x": 3, "y": 3, "color": "black", "kind": "queen"}, {"x": 0, "y": 0, "color": "black", "kind": "king"}]}, {"turn": "black", "heuristic": -9, "pieces": [{"x": 4, "y": 4, "color": "white", "kind": "king"}, {"x": 2, "y": 2, "color": "white", "kind": "queen"}, {"x": 3, "y": 3, "color": "black", "kind": "queen"}, {"x": 0, "y": 0, "color": "black", "kind": "king"}]}], "heuristic": 0, "pieces": [{"x": 4, "y": 4, "color": "white", "kind": "king"}, {"x": 2, "y": 2, "color": "white", "kind": "queen"}, {"x": 3, "y": 3, "color": "black", "kind": "queen"}, {"x": 0, "y": 0, "color": "black", "kind": "king"}]}, {"turn": "black", "old_boards": [{"turn": "white", "heuristic": -9, "pieces": [{"x": 4, "y": 4, "color": "white", "kind": "king"}, {"x": 2, "y": 2, "color": "white", "kind": "queen"}, {"x": 3, "y": 3, "color": "black", "kind": "queen"}, {"x": 0, "y": 0, "color": "black", "kind": "king"}]}, {"turn": "black", "heuristic": -9, "pieces": [{"x": 4, "y": 4, "color": "white", "kind": "king"}, {"x": 2, "y": 2, "color": "white", "kind": "queen"}, {"x": 3, "y": 3, "color": "black", "kind": "queen"}, {"x": 0, "y": 0, "color": "black", "kind": "king"}]}], "heuristic": 0, "pieces": [{"x": 4, "y": 4, "color": "white", "kind": "king"}, {"x": 2, "y": 2, "color": "white", "kind": "queen"}, {"x": 3, "y": 3, "color": "black", "kind": "queen"}, {"x": 0, "y": 0, "color": "black", "kind": "king"}]}, {"turn": "black", "old_boards": [{"turn": "white", "heuristic": -9, "pieces": [{"x": 4, "y": 4, "color": "white", "kind": "king"}, {"x": 2, "y": 2, "color": "white", "kind": "queen"}, {"x": 3, "y": 3, "color": "black", "kind": "queen"}, {"x": 0, "y": 0, "color": "black", "kind": "king"}]}, {"turn": "black", "heuristic": -9, "pieces": [{"x": 4, "y": 4, "color": "white", "kind": "king"}, {"x": 2, "y": 2, "color": "white", "kind": "queen"}, {"x": 3, "y": 3, "color": "black", "kind": "queen"}, {"x": 0, "y": 0, "color": "black", "kind": "king"}]}], "heuristic": 0, "pieces": [{"x": 4, "y": 4, "color": "white", "kind": "king"}, {"x": 1, "y": 1, "color": "white", "kind": "queen"}, {"x": 3, "y": 3, "color": "black", "kind": "queen"}, {"x": 0, "y": 0, "color": "black", "kind": "king"}]}, {"turn": "black", "old_boards": [{"turn": "white", "heuristic": -9, "pieces": [{"x": 4, "y": 4, "color": "white", "kind": "king"}, {"x": 2, "y": 2, "color": "white", "kind": "queen"}, {"x": 3, "y": 3, "color": "black", "kind": "queen"}, {"x": 0, "y": 0, "color": "black", "kind": "king"}]}, {"turn": "black", "heuristic": -9, "pieces": [{"x": 4, "y": 4, "color": "white", "kind": "king"}, {"x": 2, "y": 2, "color": "white", "kind": "queen"}, {"x": 3, "y": 3, "color": "black", "kind": "queen"}, {"x": 0, "y": 0, "color": "black", "kind": "king"}]}], "heuristic": 0, "pieces": [{"x": 4, "y": 4, "color": "white", "kind": "king"}, {"x": 0, "y": 0, "color": "white", "kind": "queen"}, {"x": 3, "y": 3, "color": "black", "kind": "queen"}, {"x": 0, "y": 0, "color": "black", "kind": "king"}]}, {"turn": "black", "old_boards": [{"turn": "white", "heuristic": -9, "pieces": [{"x": 4, "y": 4, "color": "white", "kind": "king"}, {"x": 2, "y": 2, "color": "white", "kind": "queen"}, {"x": 3, "y": 3, "color": "black", "kind": "queen"}, {"x": 0, "y": 0, "color": "black", "kind": "king"}]}, {"turn": "black", "heuristic": -9, "pieces": [{"x": 4, "y": 4, "color": "white", "kind": "king"}, {"x": 2, "y": 2, "color": "white", "kind": "queen"}, {"x": 3, "y": 3, "color": "black", "kind": "queen"}, {"x": 0, "y": 0, "color": "black", "kind": "king"}]}], "heuristic": 0, "pieces": [{"x": 4, "y": 4, "color": "white", "kind": "king"}, {"x": 3, "y": 3, "color": "white", "kind": "queen"}, {"x": 3, "y": 3, "color": "black", "kind": "queen"}, {"x": 0, "y": 0, "color": "black", "kind": "king"}]}, {"turn": "black", "old_boards": [{"turn": "white", "heuristic": 1000, "pieces": [{"x": 4, "y": 4, "color": "white", "kind": "king"}, {"x": 2, "y": 2, "color": "white", "kind": "queen"}, {"x": 3, "y": 3, "color": "black", "kind": "queen"}, {"x": 0, "y": 0, "color": "black", "kind": "king"}]}, {"turn": "black", "heuristic": -9, "pieces": [{"x": 4, "y": 4, "color": "white", "kind": "king"}, {"x": 2, "y": 2, "color": "white", "kind": "queen"}, {"x": 3, "y": 3, "color": "black", "kind": "queen"}, {"x": 0, "y": 0, "color": "black", "kind": "king"}]}], "heuristic": 0, "pieces": [{"x": 5, "y": 5, "color": "white", "kind": "king"}, {"x": 2, "y": 2, "color": "white", "kind": "queen"}, {"x": 3, "y": 3, "color": "black", "kind": "queen"}, {"x": 0, "y": 0, "color": "black", "kind": "king"}]}, {"turn": "black", "old_boards": [{"turn": "white", "heuristic": 0, "pieces": [{"x": 4, "y": 4, "color": "white", "kind": "king"}, {"x": 2, "y": 2, "color": "white", "kind": "queen"}, {"x": 3, "y": 3, "color": "black", "kind": "queen"}, {"x": 0, "y": 0, "color": "black", "kind": "king"}]}, {"turn": "black", "heuristic": -9, "pieces": [{"x": 4, "y": 4, "color": "white", "kind": "king"}, {"x": 2, "y": 2, "color": "white", "kind": "queen"}, {"x": 3, "y": 3, "color": "black", "kind": "queen"}, {"x": 0, "y": 0, "color": "black", "kind": "king"}]}], "heuristic": 0, "pieces": [{"x": 5, "y": 5, "color": "white", "kind": "king"}, {"x": 2, "y": 2, "color": "white", "kind": "queen"}, {"x": 3, "y": 3, "color": "black", "kind": "queen"}, {"x": 0, "y": 0, "color": "black", "kind": "king"}]}, {"turn": "black", "old_boards": [{"turn": "white", "heuristic": 0, "pieces": [{"x": 4, "y": 4, "color": "white", "kind": "king"}, {"x": 2, "y": 2, "color": "white", "kind": "queen"}, {"x": 3, "y": 3, "color": "black", "kind": "queen"}, {"x": 0, "y": 0, "color": "black", "kind": "king"}]}, {"turn": "black", "heuristic": -9, "pieces": [{"x": 4, "y": 4, "color": "white", "kind": "king"}, {"x": 2, "y": 2, "color": "white", "kind": "queen"}, {"x": 3, "y": 3, "color": "black", "kind": "queen"}, {"x": 0, "y": 0, "color": "black", "kind": "king"}]}], "heuristic": 0, "pieces": [{"x": 4, "y": 4, "color": "white", "kind": "king"}, {"x": 2, "y": 2, "color": "white", "kind": "queen"}, {"x": 3, "y": 3, "color": "black", "kind": "queen"}, {"x": 0, "y": 0, "color": "black", "kind": "king"}]}, {"turn": "black", "old_boards": [{"turn": "white", "heuristic": 0, "pieces": [{"x": 4, "y": 4, "color": "white", "kind": "king"}, {"x": 2, "y": 2, "color": "white", "kind": "queen"}, {"x": 3, "y": 3, "color": "black", "kind": "queen"}, {"x": 0, "y": 0, "color": "black", "kind": "king"}]}, {"turn": "black", "heuristic": -9, "pieces": [{"x": 4, "y": 4, "color": "white", "kind": "king"}, {"x": 2, "y": 2, "color": "white", "kind": "queen"}, {"x": 3, "y": 3, "color": "black", "kind": "queen"}, {"x": 0, "y": 0, "color": "black", "kind": "king"}]}], "heuristic": -9, "pieces": [{"x": 4, "y": 4, "color": "white", "kind": "king"}, {"x": 3, "y": 3, "color": "white", "kind": "queen"}, {"x": 0, "y": 0, "color": "black", "kind": "king"}]}, {"turn": "black", "old_boards": [{"turn": "white", "heuristic": -9, "pieces": [{"x": 4, "y": 4, "color": "white", "kind": "king"}, {"x": 2, "y": 2, "color": "white", "kind": "queen"}, {"x": 3, "y": 3, "color": "black", "kind": "queen"}, {"x": 0, "y": 0, "color": "black", "kind": "king"}]}, {"turn": "black", "heuristic": -9, "pieces": [{"x": 4, "y": 4, "color": "white", "kind": "king"}, {"x": 2, "y": 2, "color": "white", "kind": "queen"}, {"x": 3, "y": 3, "color": "black", "kind": "queen"}, {"x": 0, "y": 0, "color": "black", "kind": "king"}]}], "heuristic": 0, "pieces": [{"x": 4, "y": 4, "color": "white", "kind": "king"}, {"x": 1, "y": 1, "color": "white", "kind": "queen"}, {"x": 3, "y": 3, "color": "black", "kind": "queen"}, {"x": 0, "y": 0, "color": "black", "kind": "king"}]}, {"turn": "black", "old_boards": [{"turn": "white", "heuristic": -9, "pieces": [{"x": 4, "y": 4, "color": "white", "kind": "king"}, {"x": 2, "y": 2, "color": "white", "kind": "queen"}, {"x": 3, "y": 3, "color": "black", "kind": "queen"}, {"x": 0, "y": 0, "color": "black", "kind": "king"}]}, {"turn": "black", "heuristic": -9, "pieces": [{"x": 4, "y": 4, "color": "white", "kind": "king"}, {"x": 2, "y": 2, "color": "white", "kind": "queen"}, {"x": 3, "y": 3, "color": "black", "kind": "queen"}, {"x": 0, "y": 0, "color": "black", "kind": "king"}]}], "heuristic": 0, "pieces": [{"x": 4, "y": 4, "color": "white", "kind": "king"}, {"x": 0, "y": 0, "color": "white", "kind": "queen"}, {"x": 3, "y": 3, "color": "black", "kind": "queen"}, {"x": 0, "y": 0, "color": "black", "kind": "king"}]}, {"turn": "black", "old_boards": [{"turn": "white", "heuristic": -9, "pieces": [{"x": 4, "y": 4, "color": "white", "kind": "king"}, {"x": 2, "y": 2, "color": "white", "kind": "queen"}, {"x": 3, "y": 3, "color": "black", "kind": "queen"}, {"x": 0, "y": 0, "color": "black", "kind": "king"}]}, {"turn": "black", "heuristic": -9, "pieces": [{"x": 4, "y": 4, "color": "white", "kind": "king"}, {"x": 2, "y": 2, "color": "white", "kind": "queen"}, {"x": 3, "y": 3, "color": "black", "kind": "queen"}, {"x": 0, "y": 0, "color": "black", "kind": "king"}]}], "heuristic": 0, "pieces": [{"x": 4, "y": 4, "color": "white", "kind": "king"}, {"x": 2, "y": 2, "color": "white", "kind": "queen"}, {"x": 3, "y": 3, "color": "black", "kind": "queen"}, {"x": 0, "y": 0, "color": "black", "kind": "king"}]}, {"turn": "black", "old_boards": [{"turn": "white", "heuristic": -9, "pieces": [{"x": 4, "y": 4, "color": "white", "kind": "king"}, {"x": 2, "y": 2, "color": "white", "kind": "queen"}, {"x": 3, "y": 3, "color": "black", "kind": "queen"}, {"x": 0, "y": 0, "color": "black", "kind": "king"}]}, {"turn": "black", "heuristic": -9, "pieces": [{"x": 4, "y": 4, "color": "white", "kind": "king"}, {"x": 2, "y": 2, "color": "white", "kind": "queen"}, {"x": 3, "y": 3, "color": "black", "kind": "queen"}, {"x": 0, "y": 0, "color": "black", "kind": "king"}]}], "heuristic": 0, "pieces": [{"x": 4, "y": 4, "color": "white", "kind": "king"}, {"x": 2, "y": 2, "color": "white", "kind": "queen"}, {"x": 3, "y": 3, "color": "black", "kind": "queen"}, {"x": 0, "y": 0, "color": "black", "kind": "king"}]}, {"turn": "black", "old_boards": [{"turn": "white", "heuristic": -9, "pieces": [{"x": 4, "y": 4, "color": "white", "kind": "king"}, {"x": 2, "y": 2, "color": "white", "kind": "queen"}, {"x": 3, "y": 3, "color": "black", "kind": "queen"}, {"x": 0, "y": 0, "color": "black", "kind": "king"}]}, {"turn": "black", "heuristic": -9, "pieces": [{"x": 4, "y": 4, "color": "white", "kind": "king"}, {"x": 2, "y": 2, "color": "white", "kind": "queen"}, {"x": 3, "y": 3, "color": "black", "kind": "queen"}, {"x": 0, "y": 0, "color": "black", "kind": "king"}]}], "heuristic": 0, "pieces": [{"x": 4, "y": 4, "color": "white", "kind": "king"}, {"x": 2, "y": 2, "color": "white", "kind": "queen"}, {"x": 3, "y": 3, "color": "black", "kind": "queen"}, {"x": 0, "y": 0, "color": "black", "kind": "king"}]}, {"turn": "black", "old_boards": [{"turn": "white", "heuristic": -9, "pieces": [{"x": 4, "y": 4, "color": "white", "kind": "king"}, {"x": 2, "y": 2, "color": "white", "kind": "queen"}, {"x": 3, "y": 3, "color": "black", "kind": "queen"}, {"x": 0, "y": 0, "color": "black", "kind": "king"}]}, {"turn": "black", "heuristic": -9, "pieces": [{"x": 4, "y": 4, "color": "white", "kind": "king"}, {"x": 2, "y": 2, "color": "white", "kind": "queen"}, {"x": 3, "y": 3, "color": "black", "kind": "queen"}, {"x": 0, "y": 0, "color": "black", "kind": "king"}]}], "heuristic": 0, "pieces": [{"x": 4, "y": 4, "color": "white", "kind": "king"}, {"x": 2, "y": 2, "color": "white", "kind": "queen"}, {"x": 3, "y": 3, "color": "black", "kind": "queen"}, {"x": 0, "y": 0, "color": "black", "kind": "king"}]}, {"turn": "black", "old_boards": [{"turn": "white", "heuristic": -9, "pieces": [{"x": 4, "y": 4, "color": "white", "kind": "king"}, {"x": 2, "y": 2, "color": "white", "kind": "queen"}, {"x": 3, "y": 3, "color": "black", "kind": "queen"}, {"x": 0, "y": 0, "color": "black", "kind": "king"}]}, {"turn": "black", "heuristic": -9, "pieces": [{"x": 4, "y": 4, "color": "white", "kind": "king"}, {"x": 2, "y": 2, "color": "white", "kind": "queen"}, {"x": 3, "y": 3, "color": "black", "kind": "queen"}, {"x": 0, "y": 0, "color": "black", "kind": "king"}]}], "heuristic": 0, "pieces": [{"x": 4, "y": 4, "color": "white", "kind": "king"}, {"x": 2, "y": 2, "color": "white", "kind": "queen"}, {"x": 3, "y": 3, "color": "black", "kind": "queen"}, {"x": 0, "y": 0, "color": "black", "kind": "king"}]}, {"turn": "black", "old_boards": [{"turn": "white", "heuristic": -9, "pieces": [{"x": 4, "y": 4, "color": "white", "kind": "king"}, {"x": 2, "y": 2, "color": "white", "kind": "queen"}, {"x": 3, "y": 3, "color": "black", "kind": "queen"}, {"x": 0, "y": 0, "color": "black", "kind": "king"}]}, {"turn": "black", "heuristic": -9, "pieces": [{"x": 4, "y": 4, "color": "white", "kind": "king"}, {"x": 2, "y": 2, "color": "white", "kind": "queen"}, {"x": 3, "y": 3, "color": "black", "kind": "queen"}, {"x": 0, "y": 0, "color": "black", "kind": "king"}]}], "heuristic": 0, "pieces": [{"x": 4, "y": 4, "color": "white", "kind": "king"}, {"x": 2, "y": 2, "color": "white", "kind": "queen"}, {"x": 3, "y": 3, "color": "black", "kind": "queen"}, {"x": 0, "y": 0, "color": "black", "kind": "king"}]}, {"turn": "black", "old_boards": [{"turn": "white", "heuristic": -9, "pieces": [{"x": 4, "y": 4, "color": "white", "kind": "king"}, {"x": 2, "y": 2, "color": "white", "kind": "queen"}, {"x": 3, "y": 3, "color": "black", "kind": "queen"}, {"x": 0, "y": 0, "color": "black", "kind": "king"}]}, {"turn": "black", "heuristic": -9, "pieces": [{"x": 4, "y": 4, "color": "white", "kind": "king"}, {"x": 2, "y": 2, "color": "white", "kind": "queen"}, {"x": 3, "y": 3, "color": "black", "kind": "queen"}, {"x": 0, "y": 0, "color": "black", "kind": "king"}]}], "heuristic": 0, "pieces": [{"x": 4, "y": 4, "color": "white", "kind": "king"}, {"x": 2, "y": 2, "color": "white", "kind": "queen"}, {"x": 3, "y": 3, "color": "black", "kind": "queen"}, {"x": 0, "y": 0, "color": "black", "kind": "king"}]}, {"turn": "black", "old_boards": [{"turn": "white", "heuristic": -9, "pieces": [{"x": 4, "y": 4, "color": "white", "kind": "king"}, {"x": 2, "y": 2, "color": "white", "kind": "queen"}, {"x": 3, "y": 3, "color": "black", "kind": "queen"}, {"x": 0, "y": 0, "color": "black", "kind": "king"}]}, {"turn": "black", "heuristic": -9, "pieces": [{"x": 4, "y": 4, "color": "white", "kind": "king"}, {"x": 2, "y": 2, "color": "white", "kind": "queen"}, {"x": 3, "y": 3, "color": "black", "kind": "queen"}, {"x": 0, "y": 0, "color": "black", "kind": "king"}]}], "heuristic": 0, "pieces": [{"x": 4, "y": 4, "color": "white", "kind": "king"}, {"x": 1, "y": 1, "color": "white", "kind": "queen"}, {"x": 3, "y": 3, "color": "black", "kind": "queen"}, {"x": 0, "y": 0, "color": "black", "kind": "king"}]}, {"turn": "black", "old_boards": [{"turn": "white", "heuristic": -9, "pieces": [{"x": 4, "y": 4, "color": "white", "kind": "king"}, {"x": 2, "y": 2, "color": "white", "kind": "queen"}, {"x": 3, "y": 3, "color": "black", "kind": "queen"}, {"x": 0, "y": 0, "color": "black", "kind": "king"}]}, {"turn": "black", "heuristic": -9, "pieces": [{"x": 4, "y": 4, "color": "white", "kind": "king"}, {"x": 2, "y": 2, "color": "white", "kind": "queen"}, {"x": 3, "y": 3, "color": "black", "kind": "queen"}, {"x": 0, "y": 0, "color": "black", "kind": "king"}]}], "heuristic": 0, "pieces": [{"x": 4, "y": 4, "color": "white", "kind": "king"}, {"x": 0, "y": 0, "color": "white", "kind": "queen"}, {"x": 3, "y": 3, "color": "black", "kind": "queen"}, {"x": 0, "y": 0, "color": "black", "kind": "king"}]}, {"turn": "black", "old_boards": [{"turn": "white", "heuristic": -9, "pieces": [{"x": 4, "y": 4, "color": "white", "kind": "king"}, {"x": 2, "y": 2, "color": "white", "kind": "queen"}, {"x": 3, "y": 3, "color": "black", "kind": "queen"}, {"x": 0, "y": 0, "color": "black", "kind": "king"}]}, {"turn": "black", "heuristic": -9, "pieces": [{"x": 4, "y": 4, "color": "white", "kind": "king"}, {"x": 2, "y": 2, "color": "white", "kind": "queen"}, {"x": 3, "y": 3, "color": "black", "kind": "queen"}, {"x": 0, "y": 0, "color": "black", "kind": "king"}]}], "heuristic": 0, "pieces": [{"x": 4, "y": 4, "color": "white", "kind": "king"}, {"x": 3, "y": 3, "color": "white", "kind": "queen"}, {"x": 3, "y": 3, "color": "black", "kind": "queen"}, {"x": 0, "y": 0, "color": "black", "kind": "king"}]}]}